Workbook
Name CARROT_BED_CAP: Inputs!$B$7
Name CARROT_BEDS: Optimization!$B$3
Name CARROT_DIM: Inputs!$B$10
Name CARROT_FERT: Inputs!$B$11
Name CARROT_HRS: Inputs!$B$9
Name CARROT_REVENUE: Inputs!$B$8
Name FIXED_COSTS: Inputs!$B$19
Name MESCLUN_BED_CAP: Inputs!$B$12
Name MESCLUN_BEDS: Optimization!$B$4
Name MESCLUN_DIM: Inputs!$B$15
Name MESCLUN_FERT: Inputs!$B$16
Name MESCLUN_HRS: Inputs!$B$14
Name MESCLUN_REVENUE: Inputs!$B$13
Name OWNER_HRS: Inputs!$B$20
Name OWNER_RATE: Inputs!$B$21
Name PROFIT_CELL_NOTE: CostStructure!$B$32
Name SEASON_WEEKS: Inputs!$B$18
Name TEMP_HRS_EACH: Inputs!$B$23
Name TEMP_RATE: Inputs!$B$24
Name TEMP_WORKER_CAP: Inputs!$B$22
Name TOMATO_BED_CAP: Inputs!$B$2
Name TOMATO_BEDS: Optimization!$B$2
Name TOMATO_DIM: Inputs!$B$5
Name TOMATO_FERT: Inputs!$B$6
Name TOMATO_HRS: Inputs!$B$4
Name TOMATO_REVENUE: Inputs!$B$3
Name TOTAL_BEDS: Inputs!$B$17

Sheet Inputs
A1: Name | B1: Value | C1: Unit | D1: Source
A2: TOMATO_BED_CAP | B2: 20 | C2: beds | D2: case givens
A3: TOMATO_REVENUE | B3: 8800 | C3: $/bed | D3: case givens
A4: TOMATO_HRS | B4: 2.5 | C4: hrs/wk/bed | D4: case givens
A5: TOMATO_DIM | B5: 0.1 | C5: - | D5: case givens
A6: TOMATO_FERT | B6: 880 | C6: $/bed | D6: case givens
A7: CARROT_BED_CAP | B7: 20 | C7: beds | D7: case givens
A8: CARROT_REVENUE | B8: 2094 | C8: $/bed | D8: case givens
A9: CARROT_HRS | B9: =2.5/3 -> 0.83333333 | C9: hrs/wk/bed | D9: case givens
A10: CARROT_DIM | B10: 0.025 | C10: - | D10: case givens
A11: CARROT_FERT | B11: 440 | C11: $/bed | D11: case givens
A12: MESCLUN_BED_CAP | B12: 30 | C12: beds | D12: case givens
A13: MESCLUN_REVENUE | B13: 2700 | C13: $/bed | D13: case givens
A14: MESCLUN_HRS | B14: 1.25 | C14: hrs/wk/bed | D14: case givens
A15: MESCLUN_DIM | B15: 0.0125 | C15: - | D15: case givens
A16: MESCLUN_FERT | B16: 880 | C16: $/bed | D16: case givens
A17: TOTAL_BEDS | B17: 64 | C17: beds | D17: case givens
A18: SEASON_WEEKS | B18: 36 | C18: weeks | D18: case givens
A19: FIXED_COSTS | B19: 20000 | C19: $ | D19: case givens
A20: OWNER_HRS | B20: 720 | C20: hrs | D20: case givens
A21: OWNER_RATE | B21: =50000/1440 -> 34.722222 | C21: $/hr | D21: case givens
A22: TEMP_WORKER_CAP | B22: 4 | C22: workers | D22: case givens
A23: TEMP_HRS_EACH | B23: 1440 | C23: hrs | D23: case givens
A24: TEMP_RATE | B24: =25000/1440 -> 17.361111 | C24: $/hr | D24: case givens

Sheet CostStructure
A1: Labor hours needed
A2: TOMATO_LABOR_HRS | B2: =TOMATO_BEDS*TOMATO_HRS*SEASON_WEEKS*(1+TOMATO_DIM)^TOMATO_BEDS -> 2334.3682 | C2: hrs
A3: CARROT_LABOR_HRS | B3: =CARROT_BEDS*CARROT_HRS*SEASON_WEEKS*(1+CARROT_DIM)^CARROT_BEDS -> 983.16986 | C3: hrs
A4: MESCLUN_LABOR_HRS | B4: =MESCLUN_BEDS*MESCLUN_HRS*SEASON_WEEKS*(1+MESCLUN_DIM)^MESCLUN_BEDS -> 1959.678 | C4: hrs
A5: TOTAL_LABOR_HRS | B5: =B2+B3+B4 -> 5277.2161 | C5: hrs
A7: Labor allocation (owner first, then temp)
A8: OWNER_HRS_USED | B8: =MIN(OWNER_HRS,B5) -> 720 | C8: hrs
A9: TEMP_HRS_USED | B9: =MAX(0,B5-OWNER_HRS) -> 4557.2161 | C9: hrs
A10: OWNER_LABOR_COST | B10: =B8*OWNER_RATE -> 25000 | C10: $
A11: TEMP_LABOR_COST | B11: =B9*TEMP_RATE -> 79118.335 | C11: $
A12: TOTAL_LABOR_COST | B12: =B10+B11 -> 104118.34 | C12: $
A13: BLENDED_LABOR_RATE | B13: =IF(B5=0,0,B12/B5) -> 19.729784 | C13: $/hr
A14: TEMP_WORKERS_NEEDED | B14: =ROUNDUP(B9/TEMP_HRS_EACH,0) -> 4 | C14: workers
A16: Per-crop labor cost (at blended rate)
A17: TOMATO_LABOR_COST | B17: =B2*$B$13 -> 46056.581 | C17: $
A18: CARROT_LABOR_COST | B18: =B3*$B$13 -> 19397.729 | C18: $
A19: MESCLUN_LABOR_COST | B19: =B4*$B$13 -> 38664.025 | C19: $
A21: Fertilizer cost
A22: TOMATO_FERT_COST | B22: =TOMATO_BEDS*TOMATO_FERT -> 8800 | C22: $
A23: CARROT_FERT_COST | B23: =CARROT_BEDS*CARROT_FERT -> 8800 | C23: $
A24: MESCLUN_FERT_COST | B24: =MESCLUN_BEDS*MESCLUN_FERT -> 26400 | C24: $
A26: Revenue and profit
A27: TOMATO_REVENUE_TOTAL | B27: =TOMATO_BEDS*TOMATO_REVENUE -> 88000 | C27: $
A28: CARROT_REVENUE_TOTAL | B28: =CARROT_BEDS*CARROT_REVENUE -> 41880 | C28: $
A29: MESCLUN_REVENUE_TOTAL | B29: =MESCLUN_BEDS*MESCLUN_REVENUE -> 81000 | C29: $
A30: TOTAL_REVENUE | B30: =B27+B28+B29 -> 210880 | C30: $
A31: TOTAL_FERT_COST | B31: =B22+B23+B24 -> 44000 | C31: $
A32: PROFIT | B32: =B30-B31-B12-FIXED_COSTS -> 42761.665 | C32: $

Sheet Optimization
A1: Decision Variables
A2: TOMATO_BEDS | B2: 10 | C2: beds (Solver changes this)
A3: CARROT_BEDS | B3: 20 | C3: beds (Solver changes this)
A4: MESCLUN_BEDS | B4: 30 | C4: beds (Solver changes this)
A6: Constraints (Solver setup)
A7: TOMATO_BEDS <= TOMATO_BED_CAP | B7: =TOMATO_BEDS<=TOMATO_BED_CAP -> TRUE
A8: CARROT_BEDS <= CARROT_BED_CAP | B8: =CARROT_BEDS<=CARROT_BED_CAP -> TRUE
A9: MESCLUN_BEDS <= MESCLUN_BED_CAP | B9: =MESCLUN_BEDS<=MESCLUN_BED_CAP -> TRUE
A10: TOTAL BEDS <= 64 | B10: =(TOMATO_BEDS+CARROT_BEDS+MESCLUN_BEDS)<=TOTAL_BEDS -> TRUE
A11: TEMP WORKERS <= 4 | B11: =CostStructure!B20<=TEMP_WORKER_CAP -> TRUE
A12: All bed counts are INTEGER | B12: (set in Solver's Add Constraint dialog: int)
A14: Objective
A15: Maximize PROFIT | B15: =CostStructure!B32 -> 42761.665
A16: By changing: | B16: TOMATO_BEDS, CARROT_BEDS, MESCLUN_BEDS
A17: Method: | B17: GRG Nonlinear
A18: PROFIT (mirrored from CostStructure) | B18: =CostStructure!B32 -> 42761.665
A20: Constraint constants (for Solver, all on this sheet)
A21: TOMATO_CAP | B21: 20
A22: CARROT_CAP | B22: 20
A23: MESCLUN_CAP | B23: 30
A24: TOTAL_CAP | B24: 64

Sheet MarginalCostSchedules
A1: This sheet builds a standalone (single-crop) marginal cost table for each crop, | B1: beds 1 through cap, ignoring the other two crops and the 64-bed limit.
A3: Bed # | B3: Tomato Labor Hrs | C3: Tomato MC ($) | D3: Carrot Labor Hrs | E3: Carrot MC ($) | F3: Mesclun Labor Hrs | G3: Mesclun MC ($) | I3: Tomato MC, owner-first ($)
A4: 1 | B4: =IF(A4<=TOMATO_BED_CAP,A4*TOMATO_HRS*SEASON_WEEKS*(1+TOMATO_DIM)^A4,"") -> 99 | C4: =(B4*TEMP_RATE+TOMATO_FERT) -> 2598.75 | D4: =IF(A4<=CARROT_BED_CAP,A4*CARROT_HRS*SEASON_WEEKS*(1+CARROT_DIM)^A4,"") -> 30.75 | E4: =(D4*TEMP_RATE+CARROT_FERT) -> 973.85417 | F4: =A4*MESCLUN_HRS*SEASON_WEEKS*(1+MESCLUN_DIM)^A4 -> 45.5625 | G4: =(F4*TEMP_RATE+MESCLUN_FERT) -> 1671.0156 | I4: =(MIN(B4,OWNER_HRS)*OWNER_RATE+MAX(0,B4-OWNER_HRS)*TEMP_RATE)+TOMATO_FERT -> 4317.5
A5: 2 | B5: =IF(A5<=TOMATO_BED_CAP,A5*TOMATO_HRS*SEASON_WEEKS*(1+TOMATO_DIM)^A5,"") -> 217.8 | C5: =((B5-B4)*TEMP_RATE+TOMATO_FERT) -> 2942.5 | D5: =IF(A5<=CARROT_BED_CAP,A5*CARROT_HRS*SEASON_WEEKS*(1+CARROT_DIM)^A5,"") -> 63.0375 | E5: =((D5-D4)*TEMP_RATE+CARROT_FERT) -> 1000.5469 | F5: =A5*MESCLUN_HRS*SEASON_WEEKS*(1+MESCLUN_DIM)^A5 -> 92.264062 | G5: =((F5-F4)*TEMP_RATE+MESCLUN_FERT) -> 1690.791 | I5: =(MIN(B5,OWNER_HRS)*OWNER_RATE+MAX(0,B5-OWNER_HRS)*TEMP_RATE)-(MIN(B4,OWNER_HRS)*OWNER_RATE+MAX(0,B4-OWNER_HRS)*TEMP_RATE)+TOMATO_FERT -> 5005
A6: 3 | B6: =IF(A6<=TOMATO_BED_CAP,A6*TOMATO_HRS*SEASON_WEEKS*(1+TOMATO_DIM)^A6,"") -> 359.37 | C6: =((B6-B5)*TEMP_RATE+TOMATO_FERT) -> 3337.8125 | D6: =IF(A6<=CARROT_BED_CAP,A6*CARROT_HRS*SEASON_WEEKS*(1+CARROT_DIM)^A6,"") -> 96.920156 | E6: =((D6-D5)*TEMP_RATE+CARROT_FERT) -> 1028.2406 | F6: =A6*MESCLUN_HRS*SEASON_WEEKS*(1+MESCLUN_DIM)^A6 -> 140.12604 | G6: =((F6-F5)*TEMP_RATE+MESCLUN_FERT) -> 1710.9372 | I6: =(MIN(B6,OWNER_HRS)*OWNER_RATE+MAX(0,B6-OWNER_HRS)*TEMP_RATE)-(MIN(B5,OWNER_HRS)*OWNER_RATE+MAX(0,B5-OWNER_HRS)*TEMP_RATE)+TOMATO_FERT -> 5795.625
A7: 4 | B7: =IF(A7<=TOMATO_BED_CAP,A7*TOMATO_HRS*SEASON_WEEKS*(1+TOMATO_DIM)^A7,"") -> 527.076 | C7: =((B7-B6)*TEMP_RATE+TOMATO_FERT) -> 3791.5625 | D7: =IF(A7<=CARROT_BED_CAP,A7*CARROT_HRS*SEASON_WEEKS*(1+CARROT_DIM)^A7,"") -> 132.45755 | E7: =((D7-D6)*TEMP_RATE+CARROT_FERT) -> 1056.9686 | F7: =A7*MESCLUN_HRS*SEASON_WEEKS*(1+MESCLUN_DIM)^A7 -> 189.17016 | G7: =((F7-F6)*TEMP_RATE+MESCLUN_FERT) -> 1731.4603 | I7: =(MIN(B7,OWNER_HRS)*OWNER_RATE+MAX(0,B7-OWNER_HRS)*TEMP_RATE)-(MIN(B6,OWNER_HRS)*OWNER_RATE+MAX(0,B6-OWNER_HRS)*TEMP_RATE)+TOMATO_FERT -> 6703.125
A8: 5 | B8: =IF(A8<=TOMATO_BED_CAP,A8*TOMATO_HRS*SEASON_WEEKS*(1+TOMATO_DIM)^A8,"") -> 724.7295 | C8: =((B8-B7)*TEMP_RATE+TOMATO_FERT) -> 4311.4844 | D8: =IF(A8<=CARROT_BED_CAP,A8*CARROT_HRS*SEASON_WEEKS*(1+CARROT_DIM)^A8,"") -> 169.71123 | E8: =((D8-D7)*TEMP_RATE+CARROT_FERT) -> 1086.7654 | F8: =A8*MESCLUN_HRS*SEASON_WEEKS*(1+MESCLUN_DIM)^A8 -> 239.41848 | G8: =((F8-F7)*TEMP_RATE+MESCLUN_FERT) -> 1752.3667 | I8: =(MIN(B8,OWNER_HRS)*OWNER_RATE+MAX(0,B8-OWNER_HRS)*TEMP_RATE)-(MIN(B7,OWNER_HRS)*OWNER_RATE+MAX(0,B7-OWNER_HRS)*TEMP_RATE)+TOMATO_FERT -> 7660.8594
A9: 6 | B9: =IF(A9<=TOMATO_BED_CAP,A9*TOMATO_HRS*SEASON_WEEKS*(1+TOMATO_DIM)^A9,"") -> 956.64294 | C9: =((B9-B8)*TEMP_RATE+TOMATO_FERT) -> 4906.275 | D9: =IF(A9<=CARROT_BED_CAP,A9*CARROT_HRS*SEASON_WEEKS*(1+CARROT_DIM)^A9,"") -> 208.74482 | E9: =((D9-D8)*TEMP_RATE+CARROT_FERT) -> 1117.6664 | F9: =A9*MESCLUN_HRS*SEASON_WEEKS*(1+MESCLUN_DIM)^A9 -> 290.89346 | G9: =((F9-F8)*TEMP_RATE+MESCLUN_FERT) -> 1773.6627 | I9: =(MIN(B9,OWNER_HRS)*OWNER_RATE+MAX(0,B9-OWNER_HRS)*TEMP_RATE)-(MIN(B8,OWNER_HRS)*OWNER_RATE+MAX(0,B8-OWNER_HRS)*TEMP_RATE)+TOMATO_FERT -> 4906.275
A10: 7 | B10: =IF(A10<=TOMATO_BED_CAP,A10*TOMATO_HRS*SEASON_WEEKS*(1+TOMATO_DIM)^A10,"") -> 1227.6918 | C10: =((B10-B9)*TEMP_RATE+TOMATO_FERT) -> 5585.7089 | D10: =IF(A10<=CARROT_BED_CAP,A10*CARROT_HRS*SEASON_WEEKS*(1+CARROT_DIM)^A10,"") -> 249.62401 | E10: =((D10-D9)*TEMP_RATE+CARROT_FERT) -> 1149.7082 | F10: =A10*MESCLUN_HRS*SEASON_WEEKS*(1+MESCLUN_DIM)^A10 -> 343.6179 | G10: =((F10-F9)*TEMP_RATE+MESCLUN_FERT) -> 1795.3549 | I10: =(MIN(B10,OWNER_HRS)*OWNER_RATE+MAX(0,B10-OWNER_HRS)*TEMP_RATE)-(MIN(B9,OWNER_HRS)*OWNER_RATE+MAX(0,B9-OWNER_HRS)*TEMP_RATE)+TOMATO_FERT -> 5585.7089
A11: 8 | B11: =IF(A11<=TOMATO_BED_CAP,A11*TOMATO_HRS*SEASON_WEEKS*(1+TOMATO_DIM)^A11,"") -> 1543.3839 | C11: =((B11-B10)*TEMP_RATE+TOMATO_FERT) -> 6360.7668 | D11: =IF(A11<=CARROT_BED_CAP,A11*CARROT_HRS*SEASON_WEEKS*(1+CARROT_DIM)^A11,"") -> 292.4167 | E11: =((D11-D10)*TEMP_RATE+CARROT_FERT) -> 1182.9286 | F11: =A11*MESCLUN_HRS*SEASON_WEEKS*(1+MESCLUN_DIM)^A11 -> 397.615 | G11: =((F11-F10)*TEMP_RATE+MESCLUN_FERT) -> 1817.4496 | I11: =(MIN(B11,OWNER_HRS)*OWNER_RATE+MAX(0,B11-OWNER_HRS)*TEMP_RATE)-(MIN(B10,OWNER_HRS)*OWNER_RATE+MAX(0,B10-OWNER_HRS)*TEMP_RATE)+TOMATO_FERT -> 6360.7668
A12: 9 | B12: =IF(A12<=TOMATO_BED_CAP,A12*TOMATO_HRS*SEASON_WEEKS*(1+TOMATO_DIM)^A12,"") -> 1909.9376 | C12: =((B12-B11)*TEMP_RATE+TOMATO_FERT) -> 7243.7793 | D12: =IF(A12<=CARROT_BED_CAP,A12*CARROT_HRS*SEASON_WEEKS*(1+CARROT_DIM)^A12,"") -> 337.193 | E12: =((D12-D11)*TEMP_RATE+CARROT_FERT) -> 1217.3664 | F12: =A12*MESCLUN_HRS*SEASON_WEEKS*(1+MESCLUN_DIM)^A12 -> 452.90833 | G12: =((F12-F11)*TEMP_RATE+MESCLUN_FERT) -> 1839.9537 | I12: =(MIN(B12,OWNER_HRS)*OWNER_RATE+MAX(0,B12-OWNER_HRS)*TEMP_RATE)-(MIN(B11,OWNER_HRS)*OWNER_RATE+MAX(0,B11-OWNER_HRS)*TEMP_RATE)+TOMATO_FERT -> 7243.7793
A13: 10 | B13: =IF(A13<=TOMATO_BED_CAP,A13*TOMATO_HRS*SEASON_WEEKS*(1+TOMATO_DIM)^A13,"") -> 2334.3682 | C13: =((B13-B12)*TEMP_RATE+TOMATO_FERT) -> 8248.5865 | D13: =IF(A13<=CARROT_BED_CAP,A13*CARROT_HRS*SEASON_WEEKS*(1+CARROT_DIM)^A13,"") -> 384.02536 | E13: =((D13-D12)*TEMP_RATE+CARROT_FERT) -> 1253.0618 | F13: =A13*MESCLUN_HRS*SEASON_WEEKS*(1+MESCLUN_DIM)^A13 -> 509.52187 | G13: =((F13-F12)*TEMP_RATE+MESCLUN_FERT) -> 1862.874 | I13: =(MIN(B13,OWNER_HRS)*OWNER_RATE+MAX(0,B13-OWNER_HRS)*TEMP_RATE)-(MIN(B12,OWNER_HRS)*OWNER_RATE+MAX(0,B12-OWNER_HRS)*TEMP_RATE)+TOMATO_FERT -> 8248.5865
A14: 11 | B14: =IF(A14<=TOMATO_BED_CAP,A14*TOMATO_HRS*SEASON_WEEKS*(1+TOMATO_DIM)^A14,"") -> 2824.5855 | C14: =((B14-B13)*TEMP_RATE+TOMATO_FERT) -> 9390.7174 | D14: =IF(A14<=CARROT_BED_CAP,A14*CARROT_HRS*SEASON_WEEKS*(1+CARROT_DIM)^A14,"") -> 432.9886 | E14: =((D14-D13)*TEMP_RATE+CARROT_FERT) -> 1290.0561 | F14: =A14*MESCLUN_HRS*SEASON_WEEKS*(1+MESCLUN_DIM)^A14 -> 567.47999 | G14: =((F14-F13)*TEMP_RATE+MESCLUN_FERT) -> 1886.2172 | I14: =(MIN(B14,OWNER_HRS)*OWNER_RATE+MAX(0,B14-OWNER_HRS)*TEMP_RATE)-(MIN(B13,OWNER_HRS)*OWNER_RATE+MAX(0,B13-OWNER_HRS)*TEMP_RATE)+TOMATO_FERT -> 9390.7174
A15: 12 | B15: =IF(A15<=TOMATO_BED_CAP,A15*TOMATO_HRS*SEASON_WEEKS*(1+TOMATO_DIM)^A15,"") -> 3389.5026 | C15: =((B15-B14)*TEMP_RATE+TOMATO_FERT) -> 10687.589 | D15: =IF(A15<=CARROT_BED_CAP,A15*CARROT_HRS*SEASON_WEEKS*(1+CARROT_DIM)^A15,"") -> 484.15998 | E15: =((D15-D14)*TEMP_RATE+CARROT_FERT) -> 1328.392 | F15: =A15*MESCLUN_HRS*SEASON_WEEKS*(1+MESCLUN_DIM)^A15 -> 626.80744 | G15: =((F15-F14)*TEMP_RATE+MESCLUN_FERT) -> 1909.9905 | I15: =(MIN(B15,OWNER_HRS)*OWNER_RATE+MAX(0,B15-OWNER_HRS)*TEMP_RATE)-(MIN(B14,OWNER_HRS)*OWNER_RATE+MAX(0,B14-OWNER_HRS)*TEMP_RATE)+TOMATO_FERT -> 10687.589
A16: 13 | B16: =IF(A16<=TOMATO_BED_CAP,A16*TOMATO_HRS*SEASON_WEEKS*(1+TOMATO_DIM)^A16,"") -> 4039.1573 | C16: =((B16-B15)*TEMP_RATE+TOMATO_FERT) -> 12158.727 | D16: =IF(A16<=CARROT_BED_CAP,A16*CARROT_HRS*SEASON_WEEKS*(1+CARROT_DIM)^A16,"") -> 537.61931 | E16: =((D16-D15)*TEMP_RATE+CARROT_FERT) -> 1368.1134 | F16: =A16*MESCLUN_HRS*SEASON_WEEKS*(1+MESCLUN_DIM)^A16 -> 687.52941 | G16: =((F16-F15)*TEMP_RATE+MESCLUN_FERT) -> 1934.2009 | I16: =(MIN(B16,OWNER_HRS)*OWNER_RATE+MAX(0,B16-OWNER_HRS)*TEMP_RATE)-(MIN(B15,OWNER_HRS)*OWNER_RATE+MAX(0,B15-OWNER_HRS)*TEMP_RATE)+TOMATO_FERT -> 12158.727
... A23: 20 | B23: =IF(A23<=TOMATO_BED_CAP,A23*TOMATO_HRS*SEASON_WEEKS*(1+TOMATO_DIM)^A23,"") -> 12109.5 | C23: =((B23-B22)*TEMP_RATE+TOMATO_FERT) -> 29548.324 | D23: =IF(A23<=CARROT_BED_CAP,A23*CARROT_HRS*SEASON_WEEKS*(1+CARROT_DIM)^A23,"") -> 983.16986 | E23: =((D23-D22)*TEMP_RATE+CARROT_FERT) -> 1688.9455 | F23: =A23*MESCLUN_HRS*SEASON_WEEKS*(1+MESCLUN_DIM)^A23 -> 1153.8335 | G23: =((F23-F22)*TEMP_RATE+MESCLUN_FERT) -> 2116.5328 | I23: =(MIN(B23,OWNER_HRS)*OWNER_RATE+MAX(0,B23-OWNER_HRS)*TEMP_RATE)-(MIN(B22,OWNER_HRS)*OWNER_RATE+MAX(0,B22-OWNER_HRS)*TEMP_RATE)+TOMATO_FERT -> 29548.324
A24: 21 | F24: =A24*MESCLUN_HRS*SEASON_WEEKS*(1+MESCLUN_DIM)^A24 -> 1226.6692 | G24: =((F24-F23)*TEMP_RATE+MESCLUN_FERT) -> 2144.5094
A25: 22 | F25: =A25*MESCLUN_HRS*SEASON_WEEKS*(1+MESCLUN_DIM)^A25 -> 1301.1456 | G25: =((F25-F24)*TEMP_RATE+MESCLUN_FERT) -> 2172.9921
A26: 23 | F26: =A26*MESCLUN_HRS*SEASON_WEEKS*(1+MESCLUN_DIM)^A26 -> 1377.2922 | G26: =((F26-F25)*TEMP_RATE+MESCLUN_FERT) -> 2201.9894
A27: 24 | F27: =A27*MESCLUN_HRS*SEASON_WEEKS*(1+MESCLUN_DIM)^A27 -> 1455.1391 | G27: =((F27-F26)*TEMP_RATE+MESCLUN_FERT) -> 2231.5095
A28: 25 | F28: =A28*MESCLUN_HRS*SEASON_WEEKS*(1+MESCLUN_DIM)^A28 -> 1534.7171 | G28: =((F28-F27)*TEMP_RATE+MESCLUN_FERT) -> 2261.5611
A29: 26 | F29: =A29*MESCLUN_HRS*SEASON_WEEKS*(1+MESCLUN_DIM)^A29 -> 1616.0571 | G29: =((F29-F28)*TEMP_RATE+MESCLUN_FERT) -> 2292.1528
A30: 27 | F30: =A30*MESCLUN_HRS*SEASON_WEEKS*(1+MESCLUN_DIM)^A30 -> 1699.1908 | G30: =((F30-F29)*TEMP_RATE+MESCLUN_FERT) -> 2323.2935
A31: 28 | F31: =A31*MESCLUN_HRS*SEASON_WEEKS*(1+MESCLUN_DIM)^A31 -> 1784.1503 | G31: =((F31-F30)*TEMP_RATE+MESCLUN_FERT) -> 2354.992
A32: 29 | F32: =A32*MESCLUN_HRS*SEASON_WEEKS*(1+MESCLUN_DIM)^A32 -> 1870.9683 | G32: =((F32-F31)*TEMP_RATE+MESCLUN_FERT) -> 2387.2574
A33: 30 | F33: =A33*MESCLUN_HRS*SEASON_WEEKS*(1+MESCLUN_DIM)^A33 -> 1959.678 | G33: =((F33-F32)*TEMP_RATE+MESCLUN_FERT) -> 2420.0991
A35: NOTE: this standalone schedule approximates marginal labor cost at the TEMP_RATE | B35: (the marginal hour is a temp-worker hour in most realistic ranges). Cross-check against | C35: the Farm Profit Lab and note any material difference in your audit.
A37: NOTE (added during audit): column I prices tomato labor the way spec Section 3 describes: the first OWNER_HRS at OWNER_RATE, any hours after that at TEMP_RATE. It is a tomatoes-grown-alone view.
A38: Column C prices every hour at TEMP_RATE, so it never shows the owner-to-temp step-down. The material difference is tomato beds 1-5: owner-first MC peaks at bed 5 ($7,661), then falls at bed 6 ($4,906) once the 720 owner hours are used up.
A39: From bed 6 on, columns C and I are identical. Carrot and mesclun are not repeated owner-first here: in the full farm the three crops share the 720 owner hours, so a crop-alone owner-first view would overstate their early-bed costs.

Sheet Checks
A1: Validation Rule | B1: Expected | C1: Actual / Formula | D1: Pass?
A2: q=1 hand check (Tomato) | B2: 99 | C2: =1*TOMATO_HRS*SEASON_WEEKS*(1+TOMATO_DIM)^1 -> 99 | D2: =C2=B2 -> TRUE
A3: No idle beds beyond cap logic | B3: <=64 | C3: =TOMATO_BEDS+CARROT_BEDS+MESCLUN_BEDS -> 60 | D3: =C3<=TOTAL_BEDS -> TRUE
A4: Tomato beds within cap | B4: <=20 | C4: =TOMATO_BEDS -> 10 | D4: =C4<=TOMATO_BED_CAP -> TRUE
A5: Carrot beds within cap | B5: <=20 | C5: =CARROT_BEDS -> 20 | D5: =C5<=CARROT_BED_CAP -> TRUE
A6: Mesclun beds within cap | B6: <=30 | C6: =MESCLUN_BEDS -> 30 | D6: =C6<=MESCLUN_BED_CAP -> TRUE
A7: Temp workers within cap | B7: <=4 | C7: =CostStructure!B14 -> 4 | D7: =C7<=TEMP_WORKER_CAP -> TRUE
A8: Check figure: optimal mix | B8: 10 / 20 / 30 | C8: 10 / 20 / 30 confirmed by Solver run from 0/0/0
A9: Check figure: profit | B9: 42762 | C9: =CostStructure!B32 -> 42761.665 | D9: =ROUND(C9,0)=B9 -> TRUE
A11: Run Solver from 0/0/0 -> record result here: | B11: 10 / 20 / 30 beds, profit $42,761.66
A12: Run Solver from 20/0/0 -> record result here: | B12: 20 / 0 / 0 beds (stuck at starting point), profit -$84,334.37
A13: Do the two runs agree? | B13: No - Solver's answer depends on the starting point. Starting from 0/0/0 finds the correct optimum (10/20/30, profit $42,761.66). Starting from 20/0/0 gets stuck at a worse point (profit -$84,334.37).
